trading212py/__init__.py
trading212py/base.py
trading212py/config.py
trading212py/decorators.py
trading212py/t212.py
trading212py-0.1.2.dist-info/LICENSE
trading212py-0.1.2.dist-info/METADATA
trading212py-0.1.2.dist-info/WHEEL
trading212py-0.1.2.dist-info/top_level.txt
trading212py-0.1.2.dist-info/RECORD
