Metadata-Version: 2.1
Name: trading212py
Version: 0.1.2
Summary: A Python client for the Trading212 public API.
Author-email: Serdar Baran <none@g.com>
License: MIT
Project-URL: Homepage, https://github.com/serdarbaran/trading212
Project-URL: Documentation, https://github.com/serdarbaran/trading212/blob/main/README.md
Project-URL: Repository, https://github.com/serdarbaran/trading212
Project-URL: Issues, https://github.com/serdarbaran/trading212/issues
Requires-Python: >=3.12
License-File: LICENSE
Requires-Dist: requests==2.32.3
Requires-Dist: python-dotenv==1.0.1
Requires-Dist: pydantic==2.8.2
